odoo/addons/login_user_detail/README.rst
odoo/addons/login_user_detail/__init__.py
odoo/addons/login_user_detail/__manifest__.py
odoo/addons/login_user_detail/doc/RELEASE_NOTES.md
odoo/addons/login_user_detail/models/__init__.py
odoo/addons/login_user_detail/models/login_user_details.py
odoo/addons/login_user_detail/security/ir.model.access.csv
odoo/addons/login_user_detail/static/description/banner.png
odoo/addons/login_user_detail/static/description/icon.png
odoo/addons/login_user_detail/static/description/index.html
odoo/addons/login_user_detail/static/description/assets/icons/check.png
odoo/addons/login_user_detail/static/description/assets/icons/chevron.png
odoo/addons/login_user_detail/static/description/assets/icons/cogs.png
odoo/addons/login_user_detail/static/description/assets/icons/consultation.png
odoo/addons/login_user_detail/static/description/assets/icons/ecom-black.png
odoo/addons/login_user_detail/static/description/assets/icons/education-black.png
odoo/addons/login_user_detail/static/description/assets/icons/hotel-black.png
odoo/addons/login_user_detail/static/description/assets/icons/license.png
odoo/addons/login_user_detail/static/description/assets/icons/lifebuoy.png
odoo/addons/login_user_detail/static/description/assets/icons/manufacturing-black.png
odoo/addons/login_user_detail/static/description/assets/icons/pos-black.png
odoo/addons/login_user_detail/static/description/assets/icons/puzzle.png
odoo/addons/login_user_detail/static/description/assets/icons/restaurant-black.png
odoo/addons/login_user_detail/static/description/assets/icons/service-black.png
odoo/addons/login_user_detail/static/description/assets/icons/trading-black.png
odoo/addons/login_user_detail/static/description/assets/icons/training.png
odoo/addons/login_user_detail/static/description/assets/icons/update.png
odoo/addons/login_user_detail/static/description/assets/icons/user.png
odoo/addons/login_user_detail/static/description/assets/icons/wrench.png
odoo_addon_login_user_detail-16.0.1.0.0.dist-info/METADATA
odoo_addon_login_user_detail-16.0.1.0.0.dist-info/WHEEL
odoo_addon_login_user_detail-16.0.1.0.0.dist-info/top_level.txt
odoo_addon_login_user_detail-16.0.1.0.0.dist-info/RECORD
