Metadata-Version: 2.1
Name: odoo-addon-login_user_detail
Version: 16.0.1.0.0
Requires-Python: >=3.10
Requires-Dist: odoo>=16.0a,<16.1dev
Summary: Login User Details & IP Address
Home-page: https://www.cybrosys.com
License: AGPL-3
Author: Cybrosys Techno Solutions
Classifier: Programming Language :: Python
Classifier: Framework :: Odoo
Classifier: Framework :: Odoo :: 16.0
Classifier: License :: OSI Approved :: GNU Affero General Public License v3
